{
  "objectID": 102295,
  "title": "Pitcher",
  "artistDisplayName": "Design attributed to Edward C. Moore (American, 1827–1891)\nTiffany and Company (American, founded 1837)\nNew York",
  "artistDisplayBio": "",
  "objectDate": "1878",
  "objectName": "pitcher (vessel)",
  "medium": "Silver, gold, and copper",
  "dimensions": "20.3 × 12.7 × 15.2 cm (8 7/8 × 5 1/4 × 6 7/8 in.)",
  "department": "Arts of the Americas",
  "culture": "",
  "period": "",
  "dynasty": "",
  "creditLine": "Art Institute of Chicago. Purchased with funds provided by Mrs. Frank L. Sulzberger",
  "objectURL": "https://www.artic.edu/artworks/102295",
  "isPublicDomain": true,
  "primaryImage": "https://www.artic.edu/iiif/2/631ad042-02e0-e333-112d-6c8e470ad670/full/843,/0/default.jpg",
  "primaryImageMedium": "https://www.artic.edu/iiif/2/631ad042-02e0-e333-112d-6c8e470ad670/full/600,/0/default.jpg",
  "primaryImageSmall": "https://www.artic.edu/iiif/2/631ad042-02e0-e333-112d-6c8e470ad670/full/400,/0/default.jpg",
  "localImage": "102295.jpg",
  "tags": [
    "19th century"
  ]
}