{
  "objectID": 118766,
  "title": "Gemini",
  "artistDisplayName": "Victor Brauner\nRomanian, 1903–1966",
  "artistDisplayBio": "",
  "objectDate": "1938",
  "objectName": "painting",
  "medium": "Oil on canvas",
  "dimensions": "45.7 × 54.3 cm (18 × 21 7/16 in.)",
  "department": "Modern Art",
  "culture": "",
  "period": "",
  "dynasty": "",
  "creditLine": "Art Institute of Chicago. Gift of Albert A. Robin",
  "objectURL": "https://www.artic.edu/artworks/118766",
  "isPublicDomain": false,
  "primaryImage": "https://www.artic.edu/iiif/2/cf83e46d-cb8f-3864-5ee0-bdc50ea4db26/full/843,/0/default.jpg",
  "primaryImageMedium": "https://www.artic.edu/iiif/2/cf83e46d-cb8f-3864-5ee0-bdc50ea4db26/full/600,/0/default.jpg",
  "primaryImageSmall": "https://www.artic.edu/iiif/2/cf83e46d-cb8f-3864-5ee0-bdc50ea4db26/full/400,/0/default.jpg",
  "localImage": "118766.jpg",
  "tags": []
}