{
  "objectID": 119147,
  "title": "Untitled",
  "artistDisplayName": "Matta\nChilean, 1911-2002",
  "artistDisplayBio": "",
  "objectDate": "1938/39",
  "objectName": "crayon",
  "medium": "Crayon and graphite, with smudging and erasing, on ivory wove paper",
  "dimensions": "40 × 65 cm (15 3/4 × 25 5/8 in.)",
  "department": "Prints and Drawings",
  "culture": "",
  "period": "",
  "dynasty": "",
  "creditLine": "Art Institute of Chicago. Lindy and Edwin Bergman Collection",
  "objectURL": "https://www.artic.edu/artworks/119147",
  "isPublicDomain": false,
  "primaryImage": "https://www.artic.edu/iiif/2/06f1627d-337c-39a1-d3a3-d92ba33a1533/full/843,/0/default.jpg",
  "primaryImageMedium": "https://www.artic.edu/iiif/2/06f1627d-337c-39a1-d3a3-d92ba33a1533/full/600,/0/default.jpg",
  "primaryImageSmall": "https://www.artic.edu/iiif/2/06f1627d-337c-39a1-d3a3-d92ba33a1533/full/400,/0/default.jpg",
  "localImage": "119147.jpg",
  "tags": [
    "Surrealism"
  ]
}