{
  "objectID": 18415,
  "title": "Kutani-Style Sweets Tray",
  "artistDisplayName": "Japan",
  "artistDisplayBio": "",
  "objectDate": "c. 1825",
  "objectName": "stoneware",
  "medium": "Porcelain with underglaze decoration and overglaze enamels",
  "dimensions": "Diam.: 20.4 cm (8 in.)",
  "department": "Arts of Asia",
  "culture": "",
  "period": "",
  "dynasty": "",
  "creditLine": "Art Institute of Chicago. Gift of The Orientals",
  "objectURL": "https://www.artic.edu/artworks/18415",
  "isPublicDomain": true,
  "primaryImage": "https://www.artic.edu/iiif/2/e6c4e331-ad5d-8d53-530a-0c50572d0d45/full/843,/0/default.jpg",
  "primaryImageMedium": "https://www.artic.edu/iiif/2/e6c4e331-ad5d-8d53-530a-0c50572d0d45/full/600,/0/default.jpg",
  "primaryImageSmall": "https://www.artic.edu/iiif/2/e6c4e331-ad5d-8d53-530a-0c50572d0d45/full/400,/0/default.jpg",
  "localImage": "18415.jpg",
  "tags": [
    "Japanese (culture or style)"
  ]
}