{
  "objectID": 193827,
  "title": "Silence",
  "artistDisplayName": "Henri Martin",
  "objectDate": "1894/97",
  "medium": "Color transfer lithograph from three stones on grayish-ivory China paper",
  "dimensions": "Image: 49.2 × 32.5 cm (19 3/8 × 12 13/16 in.); Sheet: 57 × 43 cm (22 1/2 × 16 15/16 in.)",
  "department": "Prints and Drawings",
  "culture": "France",
  "creditLine": "Art Institute of Chicago. Print and Drawing Fund",
  "objectURL": "https://www.artic.edu/artworks/193827",
  "isPublicDomain": true,
  "image_id": "54eedc9e-0ab0-947d-f703-9c56fe9df8fe",
  "iiifImageURL": "https://www.artic.edu/iiif/2/54eedc9e-0ab0-947d-f703-9c56fe9df8fe/full/843,/0/default.jpg",
  "localImage": "193827.jpg",
  "tags": []
}