{
  "objectID": "195850",
  "title": "The Louvre, Afternoon, Rainy Weather",
  "artistDisplayName": "Camille Pissarro",
  "objectDate": "1900",
  "beginYear": "1900",
  "endYear": "1900",
  "objectName": "Painting",
  "medium": "Oil on canvas",
  "dimensions": "overall: 66.68 × 81.6 cm (26 1/4 × 32 1/8 in.)\nframed: 93.66 × 109.86 × 10.16 cm (36 7/8 × 43 1/4 × 4 in.)",
  "department": "",
  "culture": "",
  "period": "",
  "dynasty": "",
  "creditLine": "National Gallery of Art. Corcoran Collection (Edward C. and Mary Walker Collection)",
  "objectURL": "https://www.nga.gov/collection/art-object-page.195850.html",
  "isPublicDomain": true,
  "imageUUID": "f7896300-10dd-4eec-ae25-bf689ce99015",
  "iiifImageURL": "https://api.nga.gov/iiif/f7896300-10dd-4eec-ae25-bf689ce99015/full/!843,843/0/default.jpg",
  "localImage": "195850.jpg",
  "tags": []
}