{
  "objectID": "1961.220",
  "title": "Portrait of Catherine Grey, Lady Manners",
  "artistDisplayName": "Thomas Lawrence",
  "objectDate": "1794",
  "objectName": "Painting",
  "medium": "oil on canvas",
  "dimensions": "Framed: 280.5 x 185 x 9 cm (110 7/16 x 72 13/16 x 3 9/16 in.); Unframed: 255.3 x 158 cm (100 1/2 x 62 3/16 in.)",
  "department": "European Painting and Sculpture",
  "culture": "England, 18th century",
  "period": "",
  "dynasty": "",
  "creditLine": "Cleveland Museum of Art. Bequest of John D. Rockefeller Jr.",
  "objectURL": "https://clevelandart.org/art/1961.220",
  "isPublicDomain": true,
  "isOnView": true,
  "localImage": "1961.220.jpg",
  "tags": [
    "Catherine Gray, Lady Manners",
    "Lady Louisa (Tollemache) Manners (1745-1840), Later Countess of Dysart, as Juno",
    "Lady Louisa Manners, later Countess of Dysart, as Juno"
  ]
}