{
  "objectID": "1963.91",
  "title": "La Cervara, the Roman Campagna",
  "artistDisplayName": "Jean Baptiste Camille Corot",
  "objectDate": "c. 1830–31",
  "medium": "Oil on fabric",
  "dimensions": "Framed: 130 x 167.5 x 9.5 cm (51 3/16 x 65 15/16 x 3 3/4 in.); Unframed: 97.6 x 135.8 cm (38 7/16 x 53 7/16 in.)",
  "department": "Modern European Painting and Sculpture",
  "culture": "France, 19th century",
  "creditLine": "Cleveland Museum of Art. Leonard C. Hanna Jr. Fund",
  "objectURL": "https://clevelandart.org/art/1963.91",
  "isPublicDomain": true,
  "localImage": "1963.91.jpg",
  "tags": [
    "The Roman Campagna"
  ]
}
