{
  "objectID": "1963.502",
  "title": "Sleep",
  "artistDisplayName": "Jean Bernard Restout",
  "objectDate": "c. 1771",
  "medium": "Oil on canvas",
  "dimensions": "Framed: 127.5 x 160 x 14 cm (50 3/16 x 63 x 5 1/2 in.); Unframed: 97.6 x 130 cm (38 7/16 x 51 3/16 in.)",
  "department": "European Painting and Sculpture",
  "culture": "France, 18th century",
  "creditLine": "Cleveland Museum of Art. Leonard C. Hanna Jr. Fund",
  "objectURL": "https://clevelandart.org/art/1963.502",
  "isPublicDomain": true,
  "localImage": "1963.502.jpg",
  "tags": [
    "Sleep---Figure Study",
    "Somnus",
    "Allegorical Figure of Sommeil (God of Sleep)",
    "Morpheus or Allegory of Sleep"
  ]
}
