{
  "objectID": "2018.85",
  "title": "Krishna and Balarama touching the feet of Vasudeva and Devaki, from the “Vertical” Bhagavata Purana",
  "artistDisplayName": "",
  "objectDate": "c. 1700–1725",
  "objectName": "Painting",
  "medium": "Gum tempera, gold, and silver on paper",
  "dimensions": "Page: 28.5 x 21.6 cm (11 1/4 x 8 1/2 in.); Image: 24.3 x 16.5 cm (9 9/16 x 6 1/2 in.)",
  "department": "Indian and Southeast Asian Art",
  "culture": "Northern India, Pahari kingdoms",
  "period": "",
  "dynasty": "",
  "creditLine": "Cleveland Museum of Art. Purchase and partial gift from the Catherine and Ralph Benkaim Collection; Severance and Greta Millikin Purchase Fund",
  "objectURL": "https://clevelandart.org/art/2018.85",
  "isPublicDomain": true,
  "isOnView": true,
  "localImage": "2018.85.jpg",
  "tags": [
    "Vasudeva and Devaki receive homage from their sons Krishna and Balarama, A page from a Bhagavata Purana series",
    "Touching the Feet of Vasudeva and Devaki, from a Bhagavata Purana"
  ]
}