{
  "objectID": 20414,
  "title": "Eye of Maria Miles Heyward",
  "artistDisplayName": "Edward Greene Malbone",
  "artistDisplayBio": "1777–1807",
  "objectDate": "ca. 1802",
  "objectName": "Painting, miniature",
  "medium": "Watercolor on ivory",
  "dimensions": "3/8 in. (1 cm)",
  "department": "The American Wing",
  "culture": "American",
  "period": "",
  "dynasty": "",
  "creditLine": "Metropolitan Museum of Art. Dale T. Johnson Fund, 2009",
  "objectURL": "https://www.metmuseum.org/art/collection/search/20414",
  "isPublicDomain": true,
  "primaryImage": "https://images.metmuseum.org/CRDImages/ad/original/DP-40088-001.jpg",
  "primaryImageSmall": "https://images.metmuseum.org/CRDImages/ad/web-large/DP-40088-001.jpg",
  "localImage": "20414.jpg",
  "tags": [
    {
      "term": "Eyes",
      "AAT_URL": "http://vocab.getty.edu/page/aat/300400484",
      "Wikidata_URL": "https://www.wikidata.org/wiki/Q7364"
    }
  ]
}