{
  "objectID": 229356,
  "title": "Twelve Jackies",
  "artistDisplayName": "Andy Warhol\nAmerican, 1928–1987",
  "artistDisplayBio": "",
  "objectDate": "1964",
  "objectName": "silkscreen",
  "medium": "Silkscreen ink on primed linen, twelve joined canvases",
  "dimensions": "152.4 × 162.6 cm (60 × 64 in.)",
  "department": "Contemporary Art",
  "culture": "",
  "period": "",
  "dynasty": "",
  "creditLine": "Art Institute of Chicago. Gift of Edlis Neeson Collection",
  "objectURL": "https://www.artic.edu/artworks/229356",
  "isPublicDomain": false,
  "primaryImage": "https://www.artic.edu/iiif/2/239fba82-6991-9813-a555-5e8b7503be0e/full/843,/0/default.jpg",
  "primaryImageMedium": "https://www.artic.edu/iiif/2/239fba82-6991-9813-a555-5e8b7503be0e/full/600,/0/default.jpg",
  "primaryImageSmall": "https://www.artic.edu/iiif/2/239fba82-6991-9813-a555-5e8b7503be0e/full/400,/0/default.jpg",
  "localImage": "229356.jpg",
  "tags": [
    "Pop Art"
  ]
}