{
  "objectID": 237641,
  "title": "Mended Petal",
  "artistDisplayName": "Yoko Ono\nJapanese, born 1933",
  "artistDisplayBio": "",
  "objectDate": "2016",
  "objectName": "sculpture",
  "medium": "Stainless steel",
  "dimensions": "365.8 × 152.4 × 91.5 cm (144 × 60 × 36 in.)",
  "department": "Contemporary Art",
  "culture": "",
  "period": "",
  "dynasty": "",
  "creditLine": "Art Institute of Chicago. Gift of the artist and Project 120 Chicago",
  "objectURL": "https://www.artic.edu/artworks/237641",
  "isPublicDomain": false,
  "primaryImage": "https://www.artic.edu/iiif/2/06d510d2-63ef-06bc-52fa-aa7f11afdc0d/full/843,/0/default.jpg",
  "primaryImageMedium": "https://www.artic.edu/iiif/2/06d510d2-63ef-06bc-52fa-aa7f11afdc0d/full/600,/0/default.jpg",
  "primaryImageSmall": "https://www.artic.edu/iiif/2/06d510d2-63ef-06bc-52fa-aa7f11afdc0d/full/400,/0/default.jpg",
  "localImage": "237641.jpg",
  "tags": [
    "21st Century"
  ]
}