{
  "objectID": 244009,
  "title": "Court Sword and Scabbard",
  "artistDisplayName": "Martin-Guillaume Biennais (French, 1764–1843)",
  "objectDate": "c. 1810",
  "objectName": "Arms",
  "medium": "Silver, gilding, steel, mother-of-pearl, wood, leather, and textile",
  "dimensions": "H.: 98 cm (38 5/8 in.)",
  "department": "Applied Arts of Europe",
  "culture": "",
  "period": "",
  "dynasty": "",
  "creditLine": "Art Institute of Chicago. Bessie Bennett Major Acquisitions Endowment Fund; through prior acquisition of the George F. Harding Collection",
  "objectURL": "https://www.artic.edu/artworks/244009",
  "isPublicDomain": true,
  "primaryImage": "https://www.artic.edu/iiif/2/f1f1f18d-8e92-1696-dae8-06abc32cf7e5/full/843,/0/default.jpg",
  "primaryImageMedium": "https://www.artic.edu/iiif/2/f1f1f18d-8e92-1696-dae8-06abc32cf7e5/full/600,/0/default.jpg",
  "primaryImageSmall": "https://www.artic.edu/iiif/2/f1f1f18d-8e92-1696-dae8-06abc32cf7e5/full/400,/0/default.jpg",
  "localImage": "244009.jpg",
  "tags": [
    "Neoclassicism",
    "empire",
    "napoleonic"
  ]
}