{
  "objectID": 261507,
  "title": "A Spectrum of Blackness: The Search for Sedimentation in Miami",
  "artistDisplayName": "Germane Barnes\nAmerican, born 1985",
  "artistDisplayBio": "",
  "objectDate": "2021",
  "objectName": "design",
  "medium": "Inkjet prints on PhotoSatin paper mounted to Dibond panel",
  "dimensions": "53.9 × 38.1 cm (21 1/4 × 15 in.)",
  "department": "Architecture and Design",
  "culture": "",
  "period": "",
  "dynasty": "",
  "creditLine": "Art Institute of Chicago. Architecture and Design Society Fund",
  "objectURL": "https://www.artic.edu/artworks/261507",
  "isPublicDomain": false,
  "primaryImage": "https://www.artic.edu/iiif/2/49723de5-388f-2512-da8b-58827bbf893d/full/843,/0/default.jpg",
  "primaryImageMedium": "https://www.artic.edu/iiif/2/49723de5-388f-2512-da8b-58827bbf893d/full/600,/0/default.jpg",
  "primaryImageSmall": "https://www.artic.edu/iiif/2/49723de5-388f-2512-da8b-58827bbf893d/full/400,/0/default.jpg",
  "localImage": "261507.jpg",
  "tags": [
    "21st Century"
  ]
}