{
  "objectID": 271820,
  "title": "Title Plate with Rustic Fountains and Dedication, from Pastorales",
  "artistDisplayName": "Claudine Bouzonnet-Stella (French, 1636–1697)",
  "objectDate": "1667",
  "objectName": "Prints and drawing",
  "medium": "Etching in black ink (recto); engraving in black ink (verso) on cream laid paper",
  "dimensions": "Approx.: 24.6 × 31.5 cm (9 11/16 × 12 7/16 in.)",
  "department": "Prints and Drawings",
  "culture": "",
  "period": "",
  "dynasty": "",
  "creditLine": "Art Institute of Chicago. The Amanda S. Johnson and Marion J. Livingston Endowment Fund",
  "objectURL": "https://www.artic.edu/artworks/271820",
  "isPublicDomain": true,
  "primaryImage": "https://www.artic.edu/iiif/2/550135ed-b7e2-7745-4725-12ab18d71fc9/full/843,/0/default.jpg",
  "primaryImageMedium": "https://www.artic.edu/iiif/2/550135ed-b7e2-7745-4725-12ab18d71fc9/full/600,/0/default.jpg",
  "primaryImageSmall": "https://www.artic.edu/iiif/2/550135ed-b7e2-7745-4725-12ab18d71fc9/full/400,/0/default.jpg",
  "localImage": "271820.jpg",
  "tags": []
}