{
  "objectID": 273065,
  "title": "Balloons",
  "artistDisplayName": "Lynne Cohen\nCanadian, 1944-2014",
  "artistDisplayBio": "",
  "objectDate": "2007, printed 2024",
  "objectName": null,
  "medium": "Chromogenic print",
  "dimensions": "132.1 × 156.3 cm (52 × 61 1/2 in.)",
  "department": "Photography and Media",
  "culture": "",
  "period": "",
  "dynasty": "",
  "creditLine": "Art Institute of Chicago. Purchased with funds provided by Nate Pomeroy",
  "objectURL": "https://www.artic.edu/artworks/273065",
  "isPublicDomain": false,
  "primaryImage": null,
  "primaryImageMedium": null,
  "primaryImageSmall": null,
  "localImage": "273065.jpg",
  "tags": []
}