{
  "objectID": 37813,
  "title": "The Bodhisattva Maitreya, Buddha of the Future",
  "artistDisplayName": "",
  "objectDate": "11th or early 12th century",
  "objectName": "Thangka",
  "medium": "Distemper on cloth",
  "dimensions": "Overall: H. 54 1/2 in. (138.4 cm); W. 41 3/4 in. (106.1 cm)\r\nFramed: H. 76 1/2 (194.3 cm); W. 51 3/8 in. (130.5 cm); D. 2 in. (5.1 cm)",
  "department": "Asian Art",
  "culture": "Tibet",
  "period": "",
  "dynasty": "",
  "creditLine": "Metropolitan Museum of Art. Rogers Fund, 1989",
  "objectURL": "https://www.metmuseum.org/art/collection/search/37813",
  "isPublicDomain": true,
  "primaryImage": "https://images.metmuseum.org/CRDImages/as/original/23ar4_61B.jpg",
  "primaryImageSmall": "https://images.metmuseum.org/CRDImages/as/web-large/23ar4_61B.jpg",
  "localImage": "37813.jpg",
  "tags": [
    {
      "term": "Buddhism",
      "AAT_URL": "http://vocab.getty.edu/page/aat/300073738",
      "Wikidata_URL": "https://www.wikidata.org/wiki/Q748"
    },
    {
      "term": "Bodhisattvas",
      "AAT_URL": "http://vocab.getty.edu/page/aat/300264360",
      "Wikidata_URL": "https://www.wikidata.org/wiki/Q178149"
    },
    {
      "term": "Buddha",
      "AAT_URL": "http://vocab.getty.edu/page/aat/300262950",
      "Wikidata_URL": "https://www.wikidata.org/wiki/Q7055"
    }
  ]
}