{
  "objectID": 38304,
  "title": "Bust of Hevajra",
  "artistDisplayName": "",
  "artistDisplayBio": "",
  "objectDate": "late 12th–early 13th century",
  "objectName": "Bust",
  "medium": "Stone",
  "dimensions": "H. 52 in. (132.1 cm); W. 29 in. (73.7 cm)",
  "department": "Asian Art",
  "culture": "Cambodia",
  "period": "Angkor period",
  "dynasty": "",
  "creditLine": "Fletcher Fund, 1936",
  "objectURL": "https://www.metmuseum.org/art/collection/search/38304",
  "isPublicDomain": true,
  "primaryImage": "https://images.metmuseum.org/CRDImages/as/original/DT5215.jpg",
  "primaryImageSmall": "https://images.metmuseum.org/CRDImages/as/web-large/DT5215.jpg",
  "localImage": "38304.jpg",
  "tags": [
    {
      "term": "Buddhism",
      "AAT_URL": "http://vocab.getty.edu/page/aat/300073738",
      "Wikidata_URL": "https://www.wikidata.org/wiki/Q748"
    },
    {
      "term": "Deities",
      "AAT_URL": "http://vocab.getty.edu/page/aat/300343850",
      "Wikidata_URL": "https://www.wikidata.org/wiki/Q178885"
    }
  ]
}