{
  "objectID": "46077",
  "title": "Henrietta Marchant Liston (Mrs. Robert Liston)",
  "artistDisplayName": "Gilbert Stuart",
  "objectDate": "1800",
  "beginYear": "1800",
  "endYear": "1800",
  "objectName": "Painting",
  "medium": "Oil on canvas",
  "dimensions": "overall: 74 x 61.3 cm (29 1/8 x 24 1/8 in.)\nframed: 92.4 x 79.7 x 8.3 cm (36 3/8 x 31 3/8 x 3 1/4 in.)",
  "department": "",
  "culture": "",
  "period": "",
  "dynasty": "",
  "creditLine": "National Gallery of Art. Chester Dale Collection",
  "objectURL": "https://www.nga.gov/collection/art-object-page.46077.html",
  "isPublicDomain": true,
  "imageUUID": "48dcb14c-b765-4f38-93f1-158085e89829",
  "iiifImageURL": "https://api.nga.gov/iiif/48dcb14c-b765-4f38-93f1-158085e89829/full/!843,843/0/default.jpg",
  "localImage": "46077.jpg",
  "tags": []
}