{
  "objectID": "46168",
  "title": "The Crucifixion with the Converted Centurion",
  "artistDisplayName": "Lucas Cranach the Elder",
  "objectDate": "1536",
  "beginYear": "1536",
  "endYear": "1536",
  "objectName": "Painting",
  "medium": "Oil on panel",
  "dimensions": "overall: 50.8 x 34.6 cm (20 x 13 5/8 in.)\nframed: 67.6 x 51.7 x 5.3 cm (26 5/8 x 20 3/8 x 2 1/16 in.)",
  "department": "",
  "culture": "",
  "period": "",
  "dynasty": "",
  "creditLine": "National Gallery of Art. Samuel H. Kress Collection",
  "objectURL": "https://www.nga.gov/collection/art-object-page.46168.html",
  "isPublicDomain": true,
  "imageUUID": "9591f4f7-5344-4a18-9381-89d79c8f4cda",
  "iiifImageURL": "https://api.nga.gov/iiif/9591f4f7-5344-4a18-9381-89d79c8f4cda/full/!843,843/0/default.jpg",
  "localImage": "46168.jpg",
  "tags": []
}