{
  "objectID": 464443,
  "title": "Plaque with the Journey to Emmaus and Noli Me Tangere",
  "artistDisplayName": "",
  "objectDate": "ca. 1115–20",
  "objectName": "Plaque",
  "medium": "Elephant ivory, traces of gilding",
  "dimensions": "Overall: 10 5/8 x 5 1/4 x 3/4 in. (27 x 13.4 x 1.9 cm)\r\nWeight: 30.5oz. (866g)",
  "department": "Medieval Art",
  "culture": "Spanish",
  "period": "",
  "dynasty": "",
  "creditLine": "Metropolitan Museum of Art. Gift of J. Pierpont Morgan, 1917",
  "objectURL": "https://www.metmuseum.org/art/collection/search/464443",
  "isPublicDomain": true,
  "primaryImage": "https://images.metmuseum.org/CRDImages/md/original/DP287161.jpg",
  "primaryImageSmall": "https://images.metmuseum.org/CRDImages/md/web-large/DP287161.jpg",
  "localImage": "464443.jpg",
  "tags": [
    {
      "term": "Men",
      "AAT_URL": "http://vocab.getty.edu/page/aat/300025928",
      "Wikidata_URL": "https://www.wikidata.org/wiki/Q8441"
    },
    {
      "term": "Christ",
      "AAT_URL": "http://vocab.getty.edu/page/ia/901000087",
      "Wikidata_URL": "https://www.wikidata.org/wiki/Q642420"
    },
    {
      "term": "Mary Magdalene",
      "AAT_URL": "http://vocab.getty.edu/page/ia/901000161",
      "Wikidata_URL": "https://www.wikidata.org/wiki/Q63070"
    }
  ]
}