{
  "objectID": "46470",
  "title": "The Assumption of the Virgin",
  "artistDisplayName": "Nicolas Poussin",
  "objectDate": "c. 1630/1632",
  "beginYear": "1630",
  "endYear": "1632",
  "objectName": "Painting",
  "medium": "Oil on canvas",
  "dimensions": "overall: 134.4 x 98.1 cm (52 15/16 x 38 5/8 in.)\nframed: 171.8 x 135.3 x 13.7 cm (67 5/8 x 53 1/4 x 5 3/8 in.)",
  "department": "",
  "culture": "",
  "period": "",
  "dynasty": "",
  "creditLine": "National Gallery of Art. Ailsa Mellon Bruce Fund",
  "objectURL": "https://www.nga.gov/collection/art-object-page.46470.html",
  "isPublicDomain": true,
  "imageUUID": "c77f8b64-98a2-4b3c-b270-1863ece147c5",
  "iiifImageURL": "https://api.nga.gov/iiif/c77f8b64-98a2-4b3c-b270-1863ece147c5/full/!843,843/0/default.jpg",
  "localImage": "46470.jpg",
  "tags": []
}