{
  "objectID": 591865,
  "title": "Morte d'Arthur",
  "artistDisplayName": "Sir Thomas Malory",
  "artistDisplayBio": "British, 1415/18–1471",
  "objectDate": "1893",
  "objectName": "",
  "medium": "Illustrated book",
  "dimensions": "12 pts.; H: 10 1/4 in. (26 cm)",
  "department": "The Libraries",
  "culture": "London: J. M. Dent and Co., 1893",
  "period": "",
  "dynasty": "",
  "creditLine": "Metropolitan Museum of Art. ",
  "objectURL": "https://www.metmuseum.org/art/collection/search/591865",
  "isPublicDomain": true,
  "primaryImage": "https://images.metmuseum.org/CRDImages/li/original/li920.84 M292.R.jpg",
  "primaryImageSmall": "https://images.metmuseum.org/CRDImages/li/web-large/li920.84 M292.R.jpg",
  "localImage": "591865.jpg",
  "tags": null
}