{
  "objectID": 64376,
  "title": "Head and Torso of a Man from a Pair Statue",
  "artistDisplayName": "Egyptian",
  "artistDisplayBio": "",
  "objectDate": "New Kingdom, Dynasty 18 (about 1550–1295 BCE)",
  "objectName": "sculpture/stone",
  "medium": "Limestone and pigment",
  "dimensions": "45.7 × 34.3 × 20.3 cm (18 × 13 1/2 × 8 in.)",
  "department": "Arts of Africa",
  "culture": "",
  "period": "",
  "dynasty": "",
  "creditLine": "Art Institute of Chicago. W. Moses Willner Fund",
  "objectURL": "https://www.artic.edu/artworks/64376",
  "isPublicDomain": true,
  "primaryImage": "https://www.artic.edu/iiif/2/b623c3b3-0d91-3f5c-1fdc-da200ee8c4ec/full/843,/0/default.jpg",
  "primaryImageMedium": "https://www.artic.edu/iiif/2/b623c3b3-0d91-3f5c-1fdc-da200ee8c4ec/full/600,/0/default.jpg",
  "primaryImageSmall": "https://www.artic.edu/iiif/2/b623c3b3-0d91-3f5c-1fdc-da200ee8c4ec/full/400,/0/default.jpg",
  "localImage": "64376.jpg",
  "tags": [
    "egyptian"
  ]
}