{
  "objectID": 65889,
  "title": "Bowl with Boys Playing amid Peony Blossoms",
  "artistDisplayName": "China",
  "artistDisplayBio": "",
  "objectDate": "Jin dynasty (1115–1234), 12th century",
  "objectName": "bowl",
  "medium": "Ding ware; porcelain with underglaze molded decoration; metal rim",
  "dimensions": "6.4 × 21 cm (2 1/2 × 8 1/4 in.); Diam.: 21 cm (8 1/4 in.)",
  "department": "Arts of Asia",
  "culture": "",
  "period": "",
  "dynasty": "",
  "creditLine": "Art Institute of Chicago. Gift of Mrs. Florene M. Schoenborn",
  "objectURL": "https://www.artic.edu/artworks/65889",
  "isPublicDomain": true,
  "primaryImage": "https://www.artic.edu/iiif/2/4f7fc54d-6973-355c-a811-d478985e6851/full/843,/0/default.jpg",
  "primaryImageMedium": "https://www.artic.edu/iiif/2/4f7fc54d-6973-355c-a811-d478985e6851/full/600,/0/default.jpg",
  "primaryImageSmall": "https://www.artic.edu/iiif/2/4f7fc54d-6973-355c-a811-d478985e6851/full/400,/0/default.jpg",
  "localImage": "65889.jpg",
  "tags": [
    "Chinese (culture or style)"
  ]
}