{
  "objectID": "66420",
  "title": "Autumn",
  "artistDisplayName": "Winslow Homer",
  "objectDate": "1877",
  "beginYear": "1877",
  "endYear": "1877",
  "objectName": "Painting",
  "medium": "Oil on canvas",
  "dimensions": "overall: 97.1 x 58.9 cm (38 1/4 x 23 3/16 in.)\nframed: 126.4 x 91.1 x 7.9 cm (49 3/4 x 35 7/8 x 3 1/8 in.)",
  "department": "",
  "culture": "",
  "period": "",
  "dynasty": "",
  "creditLine": "National Gallery of Art. Collection of Mr. and Mrs. Paul Mellon",
  "objectURL": "https://www.nga.gov/collection/art-object-page.66420.html",
  "isPublicDomain": true,
  "imageUUID": "3d26f129-aa76-4f97-b64d-bc0d4157207c",
  "iiifImageURL": "https://api.nga.gov/iiif/3d26f129-aa76-4f97-b64d-bc0d4157207c/full/!843,843/0/default.jpg",
  "localImage": "66420.jpg",
  "tags": []
}