{
  "objectID": 68456,
  "title": "The Coronation of the Virgin",
  "artistDisplayName": "English",
  "objectDate": "15th century",
  "objectName": "Relief",
  "medium": "Alabaster with polychromy and gilding",
  "dimensions": "40 × 27.3 cm (20 1/2 × 13 in.)",
  "department": "Painting and Sculpture of Europe",
  "culture": "",
  "period": "",
  "dynasty": "",
  "creditLine": "Art Institute of Chicago. Gift of the Antiquarian Society",
  "objectURL": "https://www.artic.edu/artworks/68456",
  "isPublicDomain": true,
  "primaryImage": "https://www.artic.edu/iiif/2/ac520de9-62c2-ee82-ca25-ba35c6232276/full/843,/0/default.jpg",
  "primaryImageMedium": "https://www.artic.edu/iiif/2/ac520de9-62c2-ee82-ca25-ba35c6232276/full/600,/0/default.jpg",
  "primaryImageSmall": "https://www.artic.edu/iiif/2/ac520de9-62c2-ee82-ca25-ba35c6232276/full/400,/0/default.jpg",
  "localImage": "68456.jpg",
  "tags": [
    "15th century",
    "Renaissance"
  ]
}