{
  "objectID": 70186,
  "title": "Dragon Pendant",
  "artistDisplayName": "China",
  "objectDate": "Eastern Zhou dynasty, c. 770–256 B.C.\nc. 4th/3rd century B.C.",
  "objectName": "Pendant (jewelry)",
  "medium": "Jade",
  "dimensions": "6.1 × 1.5 × 0.4 cm (2 3/8 × 9/16 × 1/8 in.)",
  "department": "Arts of Asia",
  "culture": "",
  "period": "",
  "dynasty": "",
  "creditLine": "Art Institute of Chicago. Edward and Louise B. Sonnenschein Collection",
  "objectURL": "https://www.artic.edu/artworks/70186",
  "isPublicDomain": true,
  "primaryImage": null,
  "primaryImageMedium": null,
  "primaryImageSmall": null,
  "localImage": "70186.jpg",
  "tags": [
    "Chinese (culture or style)"
  ]
}