{
  "objectID": 70235,
  "title": "Perforated Cylinder",
  "artistDisplayName": "China",
  "objectDate": "Eastern Zhou dynasty, c. 770–256 B.C.\n5th century B.C.",
  "objectName": "Jade",
  "medium": "Jade",
  "dimensions": "15.9 × 1.9 cm (11 × 3/4 in.); Diam.: 1.9 cm (3/4 in.)",
  "department": "Arts of Asia",
  "culture": "",
  "period": "",
  "dynasty": "",
  "creditLine": "Art Institute of Chicago. Edward and Louise B. Sonnenschein Collection",
  "objectURL": "https://www.artic.edu/artworks/70235",
  "isPublicDomain": true,
  "primaryImage": null,
  "primaryImageMedium": null,
  "primaryImageSmall": null,
  "localImage": "70235.jpg",
  "tags": [
    "Chinese (culture or style)"
  ]
}