{
  "objectID": 70249,
  "title": "Plaque with Interlinked Scrolls",
  "artistDisplayName": "China",
  "objectDate": "Eastern Zhou dynasty, c. 770–256 B.C.\n7th century B.C.",
  "objectName": "Jade",
  "medium": "Jade",
  "dimensions": "2.5 × 2.2 × 0.2 cm (1 × 7/8 × 1/16 in.)",
  "department": "Arts of Asia",
  "culture": "",
  "period": "",
  "dynasty": "",
  "creditLine": "Art Institute of Chicago. Edward and Louise B. Sonnenschein Collection",
  "objectURL": "https://www.artic.edu/artworks/70249",
  "isPublicDomain": true,
  "primaryImage": null,
  "primaryImageMedium": null,
  "primaryImageSmall": null,
  "localImage": "70249.jpg",
  "tags": [
    "Chinese (culture or style)"
  ]
}