{
  "objectID": 70241,
  "title": "Plaque with Interlinked Scrolls",
  "artistDisplayName": "China",
  "artistDisplayBio": "",
  "objectDate": "Eastern Zhou dynasty, c. 770–256 B.C.\n7th century B.C.",
  "objectName": "jade",
  "medium": "Jade",
  "dimensions": "2.3 × 2 × 0.2 cm (7/8 × 3/4 × 1/16 in.)",
  "department": "Arts of Asia",
  "culture": "",
  "period": "",
  "dynasty": "",
  "creditLine": "Art Institute of Chicago. Edward and Louise B. Sonnenschein Collection",
  "objectURL": "https://www.artic.edu/artworks/70241",
  "isPublicDomain": true,
  "primaryImage": null,
  "primaryImageMedium": null,
  "primaryImageSmall": null,
  "localImage": "70241.jpg",
  "tags": [
    "Chinese (culture or style)"
  ]
}