{
  "objectID": 705290,
  "title": "Bo gu tu",
  "artistDisplayName": "Fu Wang",
  "artistDisplayBio": "Chinese, 1079–1126",
  "objectDate": "1752",
  "objectName": "",
  "medium": "",
  "dimensions": "16 volumes : illustrations ; Height: 11 13/16 in. (30 cm)",
  "department": "The Libraries",
  "culture": "",
  "period": "",
  "dynasty": "",
  "creditLine": "Metropolitan Museum of Art. ",
  "objectURL": "https://www.metmuseum.org/art/collection/search/705290",
  "isPublicDomain": true,
  "primaryImage": "https://images.metmuseum.org/CRDImages/li/original/NK7983_A1_W36_1752_01_001.jpg",
  "primaryImageSmall": "https://images.metmuseum.org/CRDImages/li/web-large/NK7983_A1_W36_1752_01_001.jpg",
  "localImage": "705290.jpg",
  "tags": null
}