{
  "objectID": 80051,
  "title": "Cann",
  "artistDisplayName": "William Cowell Jr. (American, 1713–1761)\nBoston",
  "artistDisplayBio": "",
  "objectDate": "1735–50",
  "objectName": "drinking vessel",
  "medium": "Silver",
  "dimensions": "13.3 × 13.3 × 8.9 cm (5 1/4 × 5 1/4 × 3 1/2 in.)",
  "department": "Arts of the Americas",
  "culture": "",
  "period": "",
  "dynasty": "",
  "creditLine": "Art Institute of Chicago. Purchased with funds provided by the Antiquarian Society through Mrs. C. Phillip Miller",
  "objectURL": "https://www.artic.edu/artworks/80051",
  "isPublicDomain": true,
  "primaryImage": "https://www.artic.edu/iiif/2/9dacf812-f057-124d-893b-bb284d5a3901/full/843,/0/default.jpg",
  "primaryImageMedium": "https://www.artic.edu/iiif/2/9dacf812-f057-124d-893b-bb284d5a3901/full/600,/0/default.jpg",
  "primaryImageSmall": "https://www.artic.edu/iiif/2/9dacf812-f057-124d-893b-bb284d5a3901/full/400,/0/default.jpg",
  "localImage": "80051.jpg",
  "tags": [
    "dining",
    "drinking"
  ]
}