{
  "objectID": "895",
  "title": "Advice to a Young Artist",
  "artistDisplayName": "Honoré Daumier",
  "objectDate": "1865/1868",
  "beginYear": "1865",
  "endYear": "1868",
  "objectName": "Painting",
  "medium": "Oil on canvas",
  "dimensions": "overall: 41.3 x 33 cm (16 1/4 x 13 in.)\nframed: 65.7 x 57.5 cm (25 7/8 x 22 5/8 in.)",
  "department": "",
  "culture": "",
  "period": "",
  "dynasty": "",
  "creditLine": "National Gallery of Art. Gift of Duncan Phillips",
  "objectURL": "https://www.nga.gov/collection/art-object-page.895.html",
  "isPublicDomain": true,
  "imageUUID": "b5fa4110-a05c-40cc-b75e-f21c59b4602c",
  "iiifImageURL": "https://api.nga.gov/iiif/b5fa4110-a05c-40cc-b75e-f21c59b4602c/full/!843,843/0/default.jpg",
  "localImage": "895.jpg",
  "tags": []
}