{
  "objectID": 96255,
  "title": "Bencharong (Five-Colored) Ware, Covered Jar",
  "artistDisplayName": "China, for the Thai Market",
  "objectDate": "19th century",
  "objectName": "Porcelain",
  "medium": "Porcelain painted in overglaze polychrome enamels",
  "dimensions": "Bowl with Lid: 22 × 19.5 cm (8 5/8 × 7 11/16 in.); Bowl: 14.6 × 19.5 cm (5 3/4 × 7 11/16 in.); Lid: 7.4 × 19.5 cm (2 7/8 × 7 11/16 in.)",
  "department": "Arts of Asia",
  "culture": "",
  "period": "",
  "dynasty": "",
  "creditLine": "Art Institute of Chicago. A. A. Sprague Fund",
  "objectURL": "https://www.artic.edu/artworks/96255",
  "isPublicDomain": true,
  "primaryImage": "https://www.artic.edu/iiif/2/8c28dce3-e71d-84d2-2792-d1486ecf9a5e/full/843,/0/default.jpg",
  "primaryImageMedium": "https://www.artic.edu/iiif/2/8c28dce3-e71d-84d2-2792-d1486ecf9a5e/full/600,/0/default.jpg",
  "primaryImageSmall": "https://www.artic.edu/iiif/2/8c28dce3-e71d-84d2-2792-d1486ecf9a5e/full/400,/0/default.jpg",
  "localImage": "96255.jpg",
  "tags": []
}