{
  "objectID": 9657,
  "title": "Wallpaper Panel",
  "artistDisplayName": "",
  "objectDate": "1700–1730",
  "objectName": "Wallpaper panel",
  "medium": "Paper, painted by hand and mounted on linen",
  "dimensions": "121 1/2 x 16 1/2 in. (308.6 x 41.9 cm)",
  "department": "The American Wing",
  "culture": "",
  "period": "",
  "dynasty": "",
  "creditLine": "Metropolitan Museum of Art. Cadwalader Fund, 1914",
  "objectURL": "https://www.metmuseum.org/art/collection/search/9657",
  "isPublicDomain": true,
  "primaryImage": "https://images.metmuseum.org/CRDImages/ad/original/25606.jpg",
  "primaryImageSmall": "https://images.metmuseum.org/CRDImages/ad/web-large/25606.jpg",
  "localImage": "9657.jpg",
  "tags": [
    {
      "term": "Birds",
      "AAT_URL": "http://vocab.getty.edu/page/aat/300266506",
      "Wikidata_URL": "https://www.wikidata.org/wiki/Q5113"
    },
    {
      "term": "Plants",
      "AAT_URL": "http://vocab.getty.edu/page/aat/300132360",
      "Wikidata_URL": "https://www.wikidata.org/wiki/Q756"
    }
  ]
}