{
  "objectID": "mia-1628",
  "title": "Saint Bartholomew and Saint Anthony Abbot",
  "artistDisplayName": "Mariotto di Nardo",
  "objectDate": "1408",
  "objectName": "Painting",
  "medium": "Tempera on poplar panel",
  "dimensions": "14 x 17 1/2 x 2 7/8 in. (35.56 x 44.45 x 7.3 cm) (overall)\r\n7 1/2 x 4 3/4 in. (19.05 x 12.07 cm) (St. Anthony Abbot)\r\n7 1/2 x 4 1/2 in. (19.05 x 11.43 cm) (St. Bartholomew)",
  "department": "European Art",
  "culture": "",
  "period": "",
  "dynasty": "",
  "creditLine": "Minneapolis Institute of Art. Gift of Daniel Wildenstein",
  "objectURL": "https://collections.artsmia.org/art/1628",
  "isPublicDomain": true,
  "isOnView": true,
  "localImage": "mia-1628.jpg",
  "tags": []
}