{
  "objectID": "mia-118127",
  "title": "Winter Landscape",
  "artistDisplayName": "Sakaki Hyakusen",
  "objectDate": "1751, 5th lunar month",
  "objectName": "hanging scroll",
  "medium": "Hanging scroll, ink on paper",
  "dimensions": "22 1/8 × 8 3/16 in. (56.2 × 20.8 cm) (image)\r\n47 3/4 × 11 15/16 in. (121.29 × 30.32 cm) (without roller)",
  "department": "Asian Art",
  "culture": "",
  "period": "",
  "dynasty": "",
  "creditLine": "Minneapolis Institute of Art. Gift of the Clark Center for Japanese Art & Culture",
  "objectURL": "https://collections.artsmia.org/art/118127",
  "isPublicDomain": true,
  "isOnView": true,
  "localImage": "mia-118127.jpg",
  "tags": []
}