{
  "objectID": "mia-118321",
  "title": "Birds in Snow",
  "artistDisplayName": "Nakabayashi Chikutō",
  "objectDate": "mid 19th century",
  "objectName": "hanging scroll",
  "medium": "Hanging scroll, ink on silk",
  "dimensions": "51 9/16 × 16 1/2 in. (130.97 × 41.91 cm) (image)\r\n82 1/2 × 21 13/16 in. (209.55 × 55.4 cm) (mount, without roller)",
  "department": "Asian Art",
  "culture": "",
  "period": "",
  "dynasty": "",
  "creditLine": "Minneapolis Institute of Art. The John R. Van Derlip Fund; purchase from the collection of Elizabeth and Willard Clark",
  "objectURL": "https://collections.artsmia.org/art/118321",
  "isPublicDomain": true,
  "isOnView": true,
  "localImage": "mia-118321.jpg",
  "tags": []
}