{
  "objectID": "mia-8775",
  "title": "An Arrangement with Flowers",
  "artistDisplayName": "Georgius Jacobus Van Os",
  "objectDate": "c. 1815–30",
  "objectName": "Painting",
  "medium": "Oil on canvas",
  "dimensions": "20 3/4 x 15 7/8 in. (52.71 x 40.32 cm) (canvas)\r\n26 1/4 x 22 1/4 in. (66.68 x 56.52 cm) (outer frame)",
  "department": "European Art",
  "culture": "",
  "period": "",
  "dynasty": "",
  "creditLine": "Minneapolis Institute of Art. Gift of Charles B. and Margaret L. Sweatt",
  "objectURL": "https://collections.artsmia.org/art/8775",
  "isPublicDomain": true,
  "isOnView": true,
  "localImage": "mia-8775.jpg",
  "tags": []
}